slackminion/__init__.py
slackminion/__main__.py
slackminion/bot.py
slackminion/dispatcher.py
slackminion/exceptions.py
slackminion/webserver.py
slackminion/plugin/__init__.py
slackminion/plugin/base.py
slackminion/plugin/manager.py
slackminion/plugins/__init__.py
slackminion/plugins/test.py
slackminion/plugins/core/__init__.py
slackminion/plugins/core/acl.py
slackminion/plugins/core/core.py
slackminion/plugins/core/user.py
slackminion/plugins/state/__init__.py
slackminion/plugins/state/file.py
slackminion/slack/__init__.py
slackminion/slack/connection.py
slackminion/slack/event.py
slackminion/slack/user.py
slackminion/slack/room/__init__.py
slackminion/slack/room/attributes.py
slackminion/slack/room/base.py
slackminion/slack/room/im.py
slackminion/slack/room/room.py
slackminion/templates/status.html
slackminion/utils/__init__.py
slackminion/utils/util.py
slackminion/utils/test_helpers/__init__.py
slackminion/utils/test_helpers/bot.py
slackminion/utils/test_helpers/plugin.py
slackminion/utils/test_helpers/slack.py
slackminion-0.9.9.dist-info/LICENSE
slackminion-0.9.9.dist-info/METADATA
slackminion-0.9.9.dist-info/WHEEL
slackminion-0.9.9.dist-info/entry_points.txt
slackminion-0.9.9.dist-info/top_level.txt
slackminion-0.9.9.dist-info/RECORD
