Metadata-Version: 2.1
Name: slackminion
Version: 0.9.9
Summary: A python bot framework for slack
Home-page: https://github.com/arcticfoxnv/slackminion
Author: Nick King
Author-email: UNKNOWN
License: MIT
Platform: UNKNOWN
Classifier: Programming Language :: Python
Classifier: License :: OSI Approved :: MIT License
Classifier: Operating System :: OS Independent
Classifier: Development Status :: 2 - Pre-Alpha
Classifier: Topic :: Communications :: Chat
Requires-Dist: Flask (>=0.10.1)
Requires-Dist: itsdangerous (>=0.24)
Requires-Dist: Jinja2 (>=2.6)
Requires-Dist: MarkupSafe (>=0.23)
Requires-Dist: PyYAML (>=3.10)
Requires-Dist: requests (<3.0a0,>=2.11)
Requires-Dist: six (<2.0a0,>=1.10)
Requires-Dist: slackclient (==1.3.1)
Requires-Dist: websocket-client (<0.55.0,>=0.35)
Requires-Dist: Werkzeug (>=0.10.4)
